Metadata-Version: 2.4
Name: Ais-cryoET
Version: 1.0.47
Summary: Segmentation of cryo-electron tomography data - https://ais-cryoet.readthedocs.org/ https://aiscryoet.org/
Home-page: https://github.com/bionanopatterning/Ais
Author: mgflast
Author-email: m.g.f.last@lumc.nl
License: GPL v3
Requires-Dist: imgui>=2.0.0
Requires-Dist: tensorflow==2.8.0
Requires-Dist: protobuf==3.20.0
Requires-Dist: glfw>=2.5.5
Requires-Dist: PyOpenGL>=3.1.6
Requires-Dist: numpy<2.0,>=1.23.2
Requires-Dist: mrcfile>=1.4.3
Requires-Dist: Pillow>=9.2.0
Requires-Dist: scipy>=1.11.0
Requires-Dist: tifffile>=2022.8.12
Requires-Dist: dill>=0.3.5.1
Requires-Dist: pyperclip>=1.8.2
Requires-Dist: scikit-image
Dynamic: author
Dynamic: author-email
Dynamic: description
Dynamic: description-content-type
Dynamic: home-page
Dynamic: license
Dynamic: requires-dist
Dynamic: summary
